[
  {
    "nome": "Adriana Nogueira",
    "email": "adriana.nogueira1@email.com",
    "nome_turma": "BD-01",
    "turno": "Manhã",
    "data_matricula": "2026-01-02",
    "nota1": 6.5,
    "nota2": 6.5,
    "nota3": 5.8,
    "media": 6.27
  },
  {
    "nome": "Alan Ribeiro",
    "email": "alan.ribeiro2@email.com",
    "nome_turma": "BD-01",
    "turno": "Manhã",
    "data_matricula": "2026-01-03",
    "nota1": 5.4,
    "nota2": 6.9,
    "nota3": 5.8,
    "media": 6.03
  },
  {
    "nome": "Aline Batista",
    "email": "aline.batista3@email.com",
    "nome_turma": "BD-01",
    "turno": "Manhã",
    "data_matricula": "2026-01-04",
    "nota1": 7.3,
    "nota2": 7.7,
    "nota3": 6.3,
    "media": 7.1
  },
  {
    "nome": "Amanda Queiroz",
    "email": "amanda.queiroz4@email.com",
    "nome_turma": "BD-01",
    "turno": "Manhã",
    "data_matricula": "2026-01-05",
    "nota1": 6.7,
    "nota2": 8,
    "nota3": 7.4,
    "media": 7.37
  },
  {
    "nome": "Anderson Martins",
    "email": "anderson.martins5@email.com",
    "nome_turma": "BD-01",
    "turno": "Manhã",
    "data_matricula": "2026-01-06",
    "nota1": 6.5,
    "nota2": 6.4,
    "nota3": 6.4,
    "media": 6.43
  },
  {
    "nome": "Andreia Lopes",
    "email": "andreia.lopes6@email.com",
    "nome_turma": "BD-01",
    "turno": "Manhã",
    "data_matricula": "2026-01-07",
    "nota1": 8.6,
    "nota2": 8.3,
    "nota3": 6.8,
    "media": 7.9
  },
  {
    "nome": "Arthur Freitas",
    "email": "arthur.freitas7@email.com",
    "nome_turma": "BD-01",
    "turno": "Manhã",
    "data_matricula": "2026-01-08",
    "nota1": 6.3,
    "nota2": 6.7,
    "nota3": 5.9,
    "media": 6.3
  },
  {
    "nome": "Bianca Moraes",
    "email": "bianca.moraes8@email.com",
    "nome_turma": "BD-01",
    "turno": "Manhã",
    "data_matricula": "2026-01-09",
    "nota1": 5.5,
    "nota2": 6,
    "nota3": 5,
    "media": 5.5
  },
  {
    "nome": "Brenda Carvalho",
    "email": "brenda.carvalho9@email.com",
    "nome_turma": "BD-01",
    "turno": "Manhã",
    "data_matricula": "2026-01-10",
    "nota1": 5,
    "nota2": 7.3,
    "nota3": 6.6,
    "media": 6.3
  },
  {
    "nome": "Caio Henrique Santos",
    "email": "caio.henrique.santos10@email.com",
    "nome_turma": "BD-01",
    "turno": "Manhã",
    "data_matricula": "2026-01-11",
    "nota1": 6.6,
    "nota2": 7.6,
    "nota3": 6.4,
    "media": 6.87
  },
  {
    "nome": "Camila Ferreira",
    "email": "camila.ferreira11@email.com",
    "nome_turma": "BD-01",
    "turno": "Manhã",
    "data_matricula": "2026-01-12",
    "nota1": 7.8,
    "nota2": 7.7,
    "nota3": 6.2,
    "media": 7.23
  },
  {
    "nome": "Carlos Eduardo Lima",
    "email": "carlos.eduardo.lima12@email.com",
    "nome_turma": "BD-01",
    "turno": "Manhã",
    "data_matricula": "2026-01-13",
    "nota1": 6.7,
    "nota2": 6.8,
    "nota3": 6.6,
    "media": 6.7
  },
  {
    "nome": "Cecília Barros",
    "email": "cecilia.barros13@email.com",
    "nome_turma": "BD-02",
    "turno": "Noite",
    "data_matricula": "2026-01-14",
    "nota1": 8.3,
    "nota2": 7.5,
    "nota3": 7.9,
    "media": 7.9
  },
  {
    "nome": "Cláudia Rezende",
    "email": "claudia.rezende14@email.com",
    "nome_turma": "BD-02",
    "turno": "Noite",
    "data_matricula": "2026-01-15",
    "nota1": 5.1,
    "nota2": 7,
    "nota3": 5.6,
    "media": 5.9
  },
  {
    "nome": "Daniela Azevedo",
    "email": "daniela.azevedo15@email.com",
    "nome_turma": "BD-02",
    "turno": "Noite",
    "data_matricula": "2026-01-16",
    "nota1": 6.2,
    "nota2": 6.6,
    "nota3": 7.3,
    "media": 6.7
  },
  {
    "nome": "Danilo Castro",
    "email": "danilo.castro16@email.com",
    "nome_turma": "BD-02",
    "turno": "Noite",
    "data_matricula": "2026-01-17",
    "nota1": 6.5,
    "nota2": 7.7,
    "nota3": 6.7,
    "media": 6.97
  },
  {
    "nome": "Diego Furtado",
    "email": "diego.furtado18@email.com",
    "nome_turma": "BD-02",
    "turno": "Noite",
    "data_matricula": "2026-01-19",
    "nota1": 7.3,
    "nota2": 6.6,
    "nota3": 6.2,
    "media": 6.7
  },
  {
    "nome": "Débora Viana",
    "email": "debora.viana17@email.com",
    "nome_turma": "BD-02",
    "turno": "Noite",
    "data_matricula": "2026-01-18",
    "nota1": 7.1,
    "nota2": 7.1,
    "nota3": 5.9,
    "media": 6.7
  },
  {
    "nome": "Eduarda Sales",
    "email": "eduarda.sales19@email.com",
    "nome_turma": "BD-02",
    "turno": "Noite",
    "data_matricula": "2026-01-20",
    "nota1": 8.5,
    "nota2": 7,
    "nota3": 7.7,
    "media": 7.73
  },
  {
    "nome": "Elias Moura",
    "email": "elias.moura20@email.com",
    "nome_turma": "BD-02",
    "turno": "Noite",
    "data_matricula": "2026-01-21",
    "nota1": 8.6,
    "nota2": 8.2,
    "nota3": 7.7,
    "media": 8.17
  },
  {
    "nome": "Elisa Fernandes",
    "email": "elisa.fernandes21@email.com",
    "nome_turma": "BD-02",
    "turno": "Noite",
    "data_matricula": "2026-01-22",
    "nota1": 6,
    "nota2": 6.1,
    "nota3": 6.7,
    "media": 6.27
  },
  {
    "nome": "Emerson Duarte",
    "email": "emerson.duarte22@email.com",
    "nome_turma": "BD-02",
    "turno": "Noite",
    "data_matricula": "2026-01-23",
    "nota1": 5.4,
    "nota2": 6.5,
    "nota3": 5.7,
    "media": 5.87
  },
  {
    "nome": "Estela Pires",
    "email": "estela.pires23@email.com",
    "nome_turma": "WEBF-01",
    "turno": "Tarde",
    "data_matricula": "2026-01-24",
    "nota1": 6.7,
    "nota2": 7.9,
    "nota3": 7.2,
    "media": 7.27
  },
  {
    "nome": "Fabiana Gomes",
    "email": "fabiana.gomes24@email.com",
    "nome_turma": "WEBF-01",
    "turno": "Tarde",
    "data_matricula": "2026-01-25",
    "nota1": 7.7,
    "nota2": 8.2,
    "nota3": 8.5,
    "media": 8.13
  },
  {
    "nome": "Felipe Aragão",
    "email": "felipe.aragao25@email.com",
    "nome_turma": "WEBF-01",
    "turno": "Tarde",
    "data_matricula": "2026-01-26",
    "nota1": 7.8,
    "nota2": 8.2,
    "nota3": 7.9,
    "media": 7.97
  },
  {
    "nome": "Fernanda Melo",
    "email": "fernanda.melo26@email.com",
    "nome_turma": "WEBF-01",
    "turno": "Tarde",
    "data_matricula": "2026-01-27",
    "nota1": 8.3,
    "nota2": 8.7,
    "nota3": 8.1,
    "media": 8.37
  },
  {
    "nome": "Gabriel Tavares",
    "email": "gabriel.tavares27@email.com",
    "nome_turma": "WEBF-01",
    "turno": "Tarde",
    "data_matricula": "2026-01-28",
    "nota1": 8.7,
    "nota2": 8.5,
    "nota3": 9.7,
    "media": 8.97
  },
  {
    "nome": "Giovana Matos",
    "email": "giovana.matos28@email.com",
    "nome_turma": "WEBF-01",
    "turno": "Tarde",
    "data_matricula": "2026-01-01",
    "nota1": 7,
    "nota2": 7.4,
    "nota3": 7.6,
    "media": 7.33
  },
  {
    "nome": "Gustavo Siqueira",
    "email": "gustavo.siqueira29@email.com",
    "nome_turma": "WEBF-01",
    "turno": "Tarde",
    "data_matricula": "2026-01-02",
    "nota1": 6.3,
    "nota2": 7,
    "nota3": 7.9,
    "media": 7.07
  },
  {
    "nome": "Helena Diniz",
    "email": "helena.diniz30@email.com",
    "nome_turma": "WEBF-01",
    "turno": "Tarde",
    "data_matricula": "2026-01-03",
    "nota1": 8,
    "nota2": 6.3,
    "nota3": 6.3,
    "media": 6.87
  },
  {
    "nome": "Henrique Paiva",
    "email": "henrique.paiva31@email.com",
    "nome_turma": "WEBF-01",
    "turno": "Tarde",
    "data_matricula": "2026-01-04",
    "nota1": 7.4,
    "nota2": 6.5,
    "nota3": 6.9,
    "media": 6.93
  },
  {
    "nome": "Isabela Monteiro",
    "email": "isabela.monteiro32@email.com",
    "nome_turma": "WEBB-01",
    "turno": "Noite",
    "data_matricula": "2026-01-05",
    "nota1": 7.4,
    "nota2": 8.8,
    "nota3": 9.1,
    "media": 8.43
  },
  {
    "nome": "Jonas Maciel",
    "email": "jonas.maciel35@email.com",
    "nome_turma": "WEBB-01",
    "turno": "Noite",
    "data_matricula": "2026-01-08",
    "nota1": 8.1,
    "nota2": 6.3,
    "nota3": 8.1,
    "media": 7.5
  },
  {
    "nome": "João Pedro Neves",
    "email": "joao.pedro.neves34@email.com",
    "nome_turma": "WEBB-01",
    "turno": "Noite",
    "data_matricula": "2026-01-07",
    "nota1": 9.5,
    "nota2": 8.2,
    "nota3": 10,
    "media": 9.23
  },
  {
    "nome": "Jéssica Andrade",
    "email": "jessica.andrade33@email.com",
    "nome_turma": "WEBB-01",
    "turno": "Noite",
    "data_matricula": "2026-01-06",
    "nota1": 9.7,
    "nota2": 7.9,
    "nota3": 9.3,
    "media": 8.97
  },
  {
    "nome": "Júlia Peixoto",
    "email": "julia.peixoto36@email.com",
    "nome_turma": "WEBB-01",
    "turno": "Noite",
    "data_matricula": "2026-01-09",
    "nota1": 7.1,
    "nota2": 7.3,
    "nota3": 8.5,
    "media": 7.63
  },
  {
    "nome": "Karen Cristina Alves",
    "email": "karen.cristina.alves37@email.com",
    "nome_turma": "WEBB-01",
    "turno": "Noite",
    "data_matricula": "2026-01-10",
    "nota1": 8.5,
    "nota2": 6.9,
    "nota3": 7.5,
    "media": 7.63
  },
  {
    "nome": "Larissa Nascimento",
    "email": "larissa.nascimento38@email.com",
    "nome_turma": "WEBB-01",
    "turno": "Noite",
    "data_matricula": "2026-01-11",
    "nota1": 8.1,
    "nota2": 7.7,
    "nota3": 7.3,
    "media": 7.7
  },
  {
    "nome": "Leonardo Cunha",
    "email": "leonardo.cunha39@email.com",
    "nome_turma": "WEBB-01",
    "turno": "Noite",
    "data_matricula": "2026-01-12",
    "nota1": 8,
    "nota2": 8.9,
    "nota3": 7.2,
    "media": 8.03
  },
  {
    "nome": "Letícia Moreira",
    "email": "leticia.moreira40@email.com",
    "nome_turma": "REDES-01",
    "turno": "Manhã",
    "data_matricula": "2026-01-13",
    "nota1": 6.9,
    "nota2": 6.6,
    "nota3": 5.6,
    "media": 6.37
  },
  {
    "nome": "Luana Barbosa",
    "email": "luana.barbosa42@email.com",
    "nome_turma": "REDES-01",
    "turno": "Manhã",
    "data_matricula": "2026-01-15",
    "nota1": 4,
    "nota2": 6.2,
    "nota3": 5.7,
    "media": 5.3
  },
  {
    "nome": "Lucas Vinícius Rocha",
    "email": "lucas.vinicius.rocha41@email.com",
    "nome_turma": "REDES-01",
    "turno": "Manhã",
    "data_matricula": "2026-01-14",
    "nota1": 6.7,
    "nota2": 7.4,
    "nota3": 7.1,
    "media": 7.07
  },
  {
    "nome": "Marcelo Torres",
    "email": "marcelo.torres43@email.com",
    "nome_turma": "REDES-01",
    "turno": "Manhã",
    "data_matricula": "2026-01-16",
    "nota1": 6.5,
    "nota2": 4.4,
    "nota3": 4.8,
    "media": 5.23
  },
  {
    "nome": "Mariana Rios",
    "email": "mariana.rios44@email.com",
    "nome_turma": "REDES-01",
    "turno": "Manhã",
    "data_matricula": "2026-01-17",
    "nota1": 4.6,
    "nota2": 6.4,
    "nota3": 5.1,
    "media": 5.37
  },
  {
    "nome": "Mateus Cardoso",
    "email": "mateus.cardoso45@email.com",
    "nome_turma": "REDES-01",
    "turno": "Manhã",
    "data_matricula": "2026-01-18",
    "nota1": 5.2,
    "nota2": 5.9,
    "nota3": 7,
    "media": 6.03
  },
  {
    "nome": "Milena Teodoro",
    "email": "milena.teodoro46@email.com",
    "nome_turma": "SEG-01",
    "turno": "Tarde",
    "data_matricula": "2026-01-19",
    "nota1": 7.7,
    "nota2": 6.3,
    "nota3": 6.1,
    "media": 6.7
  },
  {
    "nome": "Natália Campos",
    "email": "natalia.campos47@email.com",
    "nome_turma": "SEG-01",
    "turno": "Tarde",
    "data_matricula": "2026-01-20",
    "nota1": 8.3,
    "nota2": 7.4,
    "nota3": 7.7,
    "media": 7.8
  },
  {
    "nome": "Nicolas Pacheco",
    "email": "nicolas.pacheco48@email.com",
    "nome_turma": "SEG-01",
    "turno": "Tarde",
    "data_matricula": "2026-01-21",
    "nota1": 6.6,
    "nota2": 6.5,
    "nota3": 8.1,
    "media": 7.07
  },
  {
    "nome": "Otávio Menezes",
    "email": "otavio.menezes69@email.com",
    "nome_turma": "BD-03",
    "turno": "Tarde",
    "data_matricula": "2026-01-14",
    "nota1": 7.5,
    "nota2": 6.6,
    "nota3": 6.5,
    "media": 6.87
  },
  {
    "nome": "Patrícia Lemos",
    "email": "patricia.lemos49@email.com",
    "nome_turma": "SEG-01",
    "turno": "Tarde",
    "data_matricula": "2026-01-22",
    "nota1": 5.3,
    "nota2": 4.5,
    "nota3": 6.6,
    "media": 5.47
  },
  {
    "nome": "Paulo Ricardo Silva",
    "email": "paulo.ricardo.silva50@email.com",
    "nome_turma": "SEG-01",
    "turno": "Tarde",
    "data_matricula": "2026-01-23",
    "nota1": 6.2,
    "nota2": 6.6,
    "nota3": 4.9,
    "media": 5.9
  },
  {
    "nome": "Priscila Duarte",
    "email": "priscila.duarte70@email.com",
    "nome_turma": "BD-03",
    "turno": "Tarde",
    "data_matricula": "2026-01-15",
    "nota1": 4.5,
    "nota2": 4.9,
    "nota3": 4.2,
    "media": 4.53
  },
  {
    "nome": "Rafaela Correia",
    "email": "rafaela.correia51@email.com",
    "nome_turma": "SEG-01",
    "turno": "Tarde",
    "data_matricula": "2026-01-24",
    "nota1": 7.1,
    "nota2": 5.2,
    "nota3": 7.1,
    "media": 6.47
  },
  {
    "nome": "Ramon Vieira",
    "email": "ramon.vieira52@email.com",
    "nome_turma": "LOG-01",
    "turno": "Manhã",
    "data_matricula": "2026-01-25",
    "nota1": 6.9,
    "nota2": 6.7,
    "nota3": 7.2,
    "media": 6.93
  },
  {
    "nome": "Renata Chaves",
    "email": "renata.chaves53@email.com",
    "nome_turma": "LOG-01",
    "turno": "Manhã",
    "data_matricula": "2026-01-26",
    "nota1": 8.4,
    "nota2": 6.8,
    "nota3": 6.5,
    "media": 7.23
  },
  {
    "nome": "Ricardo Benevides",
    "email": "ricardo.benevides54@email.com",
    "nome_turma": "LOG-01",
    "turno": "Manhã",
    "data_matricula": "2026-01-27",
    "nota1": 7.8,
    "nota2": 7.1,
    "nota3": 6.8,
    "media": 7.23
  },
  {
    "nome": "Roberta Farias",
    "email": "roberta.farias55@email.com",
    "nome_turma": "LOG-01",
    "turno": "Manhã",
    "data_matricula": "2026-01-28",
    "nota1": 7.3,
    "nota2": 7,
    "nota3": 7.4,
    "media": 7.23
  },
  {
    "nome": "Rodrigo Holanda",
    "email": "rodrigo.holanda56@email.com",
    "nome_turma": "LOG-01",
    "turno": "Manhã",
    "data_matricula": "2026-01-01",
    "nota1": 5.5,
    "nota2": 5.5,
    "nota3": 6.6,
    "media": 5.87
  },
  {
    "nome": "Sabrina Mota",
    "email": "sabrina.mota57@email.com",
    "nome_turma": "LOG-01",
    "turno": "Manhã",
    "data_matricula": "2026-01-02",
    "nota1": 5.8,
    "nota2": 6.4,
    "nota3": 5.6,
    "media": 5.93
  },
  {
    "nome": "Samuel Pinheiro",
    "email": "samuel.pinheiro58@email.com",
    "nome_turma": "LOG-01",
    "turno": "Manhã",
    "data_matricula": "2026-01-03",
    "nota1": 6.3,
    "nota2": 5.5,
    "nota3": 6.1,
    "media": 5.97
  },
  {
    "nome": "Sara Beatriz Costa",
    "email": "sara.beatriz.costa59@email.com",
    "nome_turma": "WEBB-02",
    "turno": "Tarde",
    "data_matricula": "2026-01-04",
    "nota1": 6.4,
    "nota2": 8.1,
    "nota3": 7.7,
    "media": 7.4
  },
  {
    "nome": "Talita Xavier",
    "email": "talita.xavier60@email.com",
    "nome_turma": "WEBB-02",
    "turno": "Tarde",
    "data_matricula": "2026-01-05",
    "nota1": 7.2,
    "nota2": 7.8,
    "nota3": 8.9,
    "media": 7.97
  },
  {
    "nome": "Thiago Amaral",
    "email": "thiago.amaral61@email.com",
    "nome_turma": "WEBB-02",
    "turno": "Tarde",
    "data_matricula": "2026-01-06",
    "nota1": 7.3,
    "nota2": 9,
    "nota3": 8.1,
    "media": 8.13
  },
  {
    "nome": "Vanessa Guimarães",
    "email": "vanessa.guimaraes62@email.com",
    "nome_turma": "WEBB-02",
    "turno": "Tarde",
    "data_matricula": "2026-01-07",
    "nota1": 8.6,
    "nota2": 9.4,
    "nota3": 8.3,
    "media": 8.77
  },
  {
    "nome": "Vinícius Porto",
    "email": "vinicius.porto63@email.com",
    "nome_turma": "WEBF-02",
    "turno": "Noite",
    "data_matricula": "2026-01-08",
    "nota1": 7,
    "nota2": 7.5,
    "nota3": 8.2,
    "media": 7.57
  },
  {
    "nome": "Vitória Cristina Dias",
    "email": "vitoria.cristina.dias64@email.com",
    "nome_turma": "WEBF-02",
    "turno": "Noite",
    "data_matricula": "2026-01-09",
    "nota1": 7,
    "nota2": 8.1,
    "nota3": 7.8,
    "media": 7.63
  },
  {
    "nome": "Wellington Nunes",
    "email": "wellington.nunes65@email.com",
    "nome_turma": "WEBF-02",
    "turno": "Noite",
    "data_matricula": "2026-01-10",
    "nota1": 8,
    "nota2": 7.5,
    "nota3": 7.3,
    "media": 7.6
  },
  {
    "nome": "Yasmin Soares",
    "email": "yasmin.soares66@email.com",
    "nome_turma": "WEBF-02",
    "turno": "Noite",
    "data_matricula": "2026-01-11",
    "nota1": 7,
    "nota2": 7.2,
    "nota3": 7,
    "media": 7.07
  },
  {
    "nome": "Yuri Delgado",
    "email": "yuri.delgado67@email.com",
    "nome_turma": "BD-03",
    "turno": "Tarde",
    "data_matricula": "2026-01-12",
    "nota1": 7,
    "nota2": 5.8,
    "nota3": 5.6,
    "media": 6.13
  },
  {
    "nome": "Zuleica Almeida",
    "email": "zuleica.almeida68@email.com",
    "nome_turma": "BD-03",
    "turno": "Tarde",
    "data_matricula": "2026-01-13",
    "nota1": 5.8,
    "nota2": 7.6,
    "nota3": 7.6,
    "media": 7
  }
]